loadnsi/__init__.py
loadnsi/console_view.py
loadnsi/core.py
loadnsi/dtos.py
loadnsi/exceptions.py
loadnsi/file_handlers.py
loadnsi/loadnsi.py
loadnsi/logger.py
loadnsi/model_examplers.py
loadnsi/sql_builders.py
loadnsi/web_handlers.py
loadnsi-0.1.2.dist-info/licenses/LICENSE
loadnsi-0.1.2.dist-info/METADATA
loadnsi-0.1.2.dist-info/WHEEL
loadnsi-0.1.2.dist-info/entry_points.txt
loadnsi-0.1.2.dist-info/top_level.txt
loadnsi-0.1.2.dist-info/RECORD
