Metadata-Version: 2.4
Name: loadnsi
Version: 0.1.2
Summary: Utility for downloading and updating NSI fixtures
Home-page: https://github.com/Friskes/loadnsi
Author: Friskes
Author-email: Friskes <friskesx@gmail.com>
License: MIT License
Project-URL: Homepage, https://github.com/Friskes/loadnsi
Project-URL: Changelog, https://github.com/Friskes/loadnsi/releases/
Project-URL: Issues, https://github.com/Friskes/loadnsi/issues
Keywords: Django,Fixture,NSI
Classifier: Development Status :: 5 - Production/Stable
Classifier: Environment :: Web Environment
Classifier: Intended Audience :: Developers
Classifier: Operating System :: OS Independent
Classifier: License :: OSI Approved :: MIT License
Classifier: Programming Language :: Python :: 3.10
Classifier: Programming Language :: Python :: 3.11
Classifier: Programming Language :: Python :: 3.12
Classifier: Programming Language :: Python :: 3.13
Classifier: Topic :: Internet :: WWW/HTTP
Classifier: Topic :: Documentation
Classifier: Topic :: Software Development :: Code Generators
Requires-Python: >=3.10
License-File: LICENSE
Requires-Dist: click==8.1.8
Requires-Dist: bs4==0.0.2
Requires-Dist: httpx==0.28.0
Requires-Dist: aiofiles==24.1.0
Requires-Dist: tenacity==9.0.0
Requires-Dist: rich==13.9.4
Requires-Dist: python-dotenv==1.0.1
Provides-Extra: dev
Requires-Dist: pre-commit>=3.5.0; extra == "dev"
Requires-Dist: ruff==0.8.0; extra == "dev"
Requires-Dist: pytest>=7.0.1; extra == "dev"
Requires-Dist: mypy>=1.10.0; extra == "dev"
Requires-Dist: pytest-cov>=5.0.0; extra == "dev"
Provides-Extra: ci
Requires-Dist: ruff==0.8.0; extra == "ci"
Requires-Dist: pytest>=7.0.1; extra == "ci"
Requires-Dist: mypy>=1.10.0; extra == "ci"
Requires-Dist: pytest-cov>=5.0.0; extra == "ci"
Dynamic: license-file
